{
    "xpGain": {"min": 15, "max": 25, "every": 60},
    "xpBar": {"unfilled": "▱", "filled": "▰", "amount": 20},
    "blacklistedChannels": ["736299162324434985", "832924187844280321", "765642629936316417", "689588288926777345", "832929072799547403", "832929300801257502", "832929315724328970", "832929367222124564", "832929383270449182", "832932697592561684", "832933599585370132", "832934870346891354", "832934930740019220", "690041917324525599", "832980334597111848", "832980560926343208", "833364603656077322", "690012441349980251", "831872664149688320", "835217123415818241"],
    "roles": [
        {
            "lvl": 10,
            "id": "832948581367152640"
        },
        {
            "lvl": 20,
            "id": "832947005642375236"
        },
        {
            "lvl": 30,
            "id": "832949944087871519"
        },
        {
            "lvl": 40,
            "id": "832945782764208158"
        },
        {
            "lvl": 50,
            "id": "832739393574797372"
        },
        {
            "lvl": 60,
            "id": "832739795536052326"
        }
    ],
    "boosters": [
        {
            "lvl": 10,
            "booster": {
                "duration": 7200000,
                "factor": 1.5
            }
        },
        {
            "lvl": 20,
            "booster": {
                "duration": 10800000,
                "factor": 2
            }
        },
        {
            "lvl": 30,
            "booster": {
                "duration": 14400000,
                "factor": 3
            }
        },
        {
            "lvl": 40,
            "booster": {
                "duration": 21600000,
                "factor": 4
            }
        },
        {
            "lvl": 50,
            "booster": {
                "duration": 43200000,
                "factor": 6
            }
        },
        {
            "lvl": 60,
            "booster": {
                "duration": 86400000,
                "factor": 10
            }
        }
    ]
}