[
    {
        "name": "1.1",
        "date": "23.04.2021 - 17:55Uhr",
        "changes": [
            "Dieser tolle **changelog** Befehl wurde hinzugef체gt!",
            "Momo spielt jetzt **zuf채llige Spiele!** Er 채ndert es alle 5 Minuten, derzeit sind es **25 verschiedene Texte**. In Zukunft kommen noch mehr.",
            "Neue Befehle: **/avatar**, **/umfrage**, **/userinfo**"
        ]
    },
    {
        "name": "1.2",
        "date": "irgendwann",
        "changes": [
            "Neuer Oberbefehl: **/fun** mit aktion, emotion, meme, mock, ship",
            "diverse **Stabilit채tsverbesserungen**",
            "Erweiterung des **Datenbanksystems**",
            "Behebung von **Rechtschreibfehlern**"
        ]
    }
]